{
    "wiki": null, 
    "status": 4, 
    "name": "RGBHD01A", 
    "short_en": "RGB Head consists of 3 pairs of Read, Green and Blue LEDs and of one fototransistor.", 
    "image": "/doc/img/RGBHD01A_QRcode.png", 
    "longname_cs": "Hlava RGB Tykadla", 
    "longname_en": "RGB Feeler Head", 
    "autor": "", 
    "ust": null, 
    "doc_cs": "<p>None</p>", 
    "short_cs": "RGB hlava tykladla nese 3 p\u00e1ry LED diod (\u010derven\u00e1, zelen\u00e1 a modr\u00e1) a jeden fototranzitor.", 
    "doc_en": "<p>None</p>", 
    "category": "", 
    "root": "sensor/RGBFEE01A/RGBHD01A"
}