{
    "wiki": null, 
    "status": 4, 
    "name": "UNIBOX03A", 
    "short_en": "Universal metal module housing box with interchangeable front and back panels. Useful for housing construction of devices created from MLAB modules. With a pair of sidewalls printable 3D printer. Dimensions 220x160x51.5 mm. ", 
    "image": null, 
    "longname_cs": "rabi\u010dka pro permanentn\u00ed konstrukce", 
    "longname_en": "ermanent device housing box", 
    "ust": null, 
    "doc_cs": null, 
    "short_cs": "Univerz\u00e1ln\u00ed kovov\u00e1 krabi\u010dka pro zakrytov\u00e1n\u00ed permanentn\u00edch konstrukc\u00ed z modul\u016f MLAB. S dvojic\u00ed tisknuteln\u00fdch bo\u010dnic na 3D tisk\u00e1rn\u011b. Rozm\u011bry 220x160x51.5 mm. ", 
    "doc_en": null, 
    "root": "mechanical/boxes/UNIBOX03A"
}