{"wiki": "None", "status": 2, "name": "I2CHUB01B", "short_en": " The module allow conecting multiple I2C devices together. It does not consist any configurable IO. It is a simple bus multiplyer.", "image": "/doc/img/I2CHUB01B_QRcode.png", "short_cs": " Umo\u017e\u0148uje propojen\u00ed v\u011bt\u0161\u00edho po\u010dtu I2C za\u0159\u00edzen\u00ed. Neobsahuje \u017e\u00e1dnou konfigurovatelnou logiku.", "longname_en": " I2C (TWI) bus HUB ", "autor": "", "ust": "None", "doc_cs": "<p>None</p>", "longname_cs": " Hub pro sb\u011brnici I2C (TWI) ", "doc_en": "<p>None</p>", "category": "", "root": "comm_serial/I2CHUB01B"}