{
    "wiki": "None", 
    "status": 2, 
    "name": "BASE162101A", 
    "parameters": [], 
    "short_en": "MLAB base for modules constructions.", 
    "image_small": "/doc/img/BASE162101A_QRcode.jpgs", 
    "image": "/doc/img/BASE162101A_QRcode.png", 
    "longname_cs": "Základní deska", 
    "longname_en": "﻿Base board", 
    "mark": 50.0, 
    "ust": "http://www.ust.cz/shop/product_info.php?cPath=30&products_id=45", 
    "doc_cs": "<p>None</p>", 
    "short_cs": "Základní deska BASE1621 slouží jako základna pro realizaci pokusných zapojení pomocí modulů stavebnice MLAB.", 
    "doc_en": "<p>None</p>", 
    "_id": "BASE162101A", 
    "root": "mechanical/BASE162101A", 
    "author[]": [], 
    "category[]": [
        "mechanical"
    ]
}