{
    "wiki": "None", 
    "status": 4, 
    "name": "OZdual01A", 
    "parameters": [], 
    "short_en": "Construction of the module is optimized for most dual operational apmlifier in DIL8 package. Contains voltage reference.", 
    "image_small": "/doc/img/OZDUAL01A_big.jpg", 
    "image": "/doc/img/OZDUAL01A_big.jpg", 
    "longname_cs": "Dvojity operacni zesilovac", 
    "longname_en": "Dual operational amplifier", 
    "mark": 50.0, 
    "ust": "None", 
    "doc_cs": "<p>None</p>", 
    "short_cs": "Je optimalizovan pro vetsinu dvojitych operacnich zesilovacu v pouzdru DIL8. Obsahuje i napetovou referenci.", 
    "doc_en": "<p>None</p>", 
    "_id": "OZdual01A", 
    "root": "op_amps/OZdual01A", 
    "author[]": [], 
    "category[]": [
        "op_amps"
    ]
}