{
    "short_en": "", 
    "status": 3, 
    "name": "ALBASE1608", 
    "parameters": [], 
    "longname_en": "", 
    "wiki": "", 
    "short_cs": "Základní deska má 16x8 děr se standardní MLAB roztečí 400mils (10.16mm). Nahrazena deskou ALBASE1609.", 
    "image_small": "/doc/img/ALBASE1608_QRcode.jpgs", 
    "mark": 50.0, 
    "ust": "", 
    "doc_cs": "<p>Z&aacute;kladn&iacute; deska m&aacute; 16x8 děr se standardn&iacute; MLAB rozteč&iacute; 400mils (10.16mm). Vhodn&aacute; pro zař&iacute;zen&iacute; um&iacute;stiteln&aacute; do krabičky 1455N1601.</p>\n<p><strong>Nahrazena deskou ALBASE1609.</strong></p>", 
    "image": "/doc/img/ALBASE1608_QRcode.png", 
    "longname_cs": "Duralová základní deska s rozměrem 16x8 děr, vhodná pro krabičky 1455N1601", 
    "doc_en": "", 
    "_id": "ALBASE1608", 
    "root": "mechanical/ALBASE1608", 
    "author[]": [
        "ChroustJan"
    ], 
    "category[]": [
        "mechanical"
    ]
}